trojsdk/__init__.py
trojsdk/client.py
trojsdk/cmd.py
trojsdk/setup.py
trojsdk/config/__init__.py
trojsdk/config/auth.py
trojsdk/config/base.py
trojsdk/config/nlp.py
trojsdk/config/tabular.py
trojsdk/config/vision.py
trojsdk/core/__init__.py
trojsdk/core/client_utils.py
trojsdk/core/data_utils.py
trojsdk/core/troj_error.py
trojsdk/core/troj_logging.py
trojsdk/core/experiment_tools/__init__.py
trojai_sdk-0.2.4.3.dist-info/METADATA
trojai_sdk-0.2.4.3.dist-info/WHEEL
trojai_sdk-0.2.4.3.dist-info/entry_points.txt
trojai_sdk-0.2.4.3.dist-info/top_level.txt
trojai_sdk-0.2.4.3.dist-info/RECORD
