Metadata-Version: 2.1
Name: trojai-sdk
Version: 0.2.4.3
Summary: TrojAI provides the troj Python convenience package to allow users to integrate TrojAI adversarial protections and robustness metrics seamlessly into their AI development pipelines.
Home-page: https://troj.ai
Author: TrojAI
Author-email: stan.petley@troj.ai
Classifier: Programming Language :: Python :: 3
Classifier: Programming Language :: Python :: 3.6
Classifier: License :: OSI Approved :: MIT License
Classifier: Operating System :: OS Independent
Requires-Python: >=3.6
Requires-Dist: requests >=2.25
Requires-Dist: urllib3 >=1.26
Requires-Dist: numpy
Requires-Dist: dataclasses-json
Requires-Dist: dataclasses-jsonschema
Requires-Dist: pytest
Requires-Dist: python-hosts
Requires-Dist: minio
Requires-Dist: pandas
